{
    "info": {
        "_postman_id": "05e3718c-34b8-441e-b022-7cdbeee92442",
        "name": "Vegetable",
        "schema": "https://schema.getpostman.com/json/collection/v2.1.0/collection.json",
        "_exporter_id": "5599797"
    },
    "item": [
        {
            "name": "Vegetables",
            "item": [
                {
                    "name": "List",
                    "protocolProfileBehavior": {
                        "disableBodyPruning": true
                    },
                    "request": {
                        "method": "GET",
                        "header": [
                            {
                                "key": "Accept",
                                "value": "application/json",
                                "type": "text"
                            },
                            {
                                "key": "Authorization",
                                "value": "Bearer {{token_api}}",
                                "type": "text"
                            }
                        ],
                        "url": {
                            "raw": "{{base_url}}vegetables/list",
                            "host": [
                                "{{base_url}}vegetables"
                            ],
                            "path": [
                                "list"
                            ]
                        }
                    },
                    "response": []
                },
                {
                    "name": "Show",
                    "protocolProfileBehavior": {
                        "disableBodyPruning": true
                    },
                    "request": {
                        "method": "GET",
                        "header": [
                            {
                                "key": "Accept",
                                "value": "application/json",
                                "type": "text"
                            },
                            {
                                "key": "Authorization",
                                "value": "Bearer {{token_api}}",
                                "type": "text"
                            }
                        ],
                        "url": {
                            "raw": "{{base_url}}vegetables/show/1",
                            "host": [
                                "{{base_url}}vegetables"
                            ],
                            "path": [
                                "show",
                                "1"
                            ]
                        }
                    },
                    "response": []
                },
                {
                    "name": "Store",
                    "request": {
                        "method": "POST",
                        "header": [
                            {
                                "key": "Accept",
                                "value": "application/json",
                                "type": "text"
                            },
                            {
                                "key": "Authorization",
                                "value": "Bearer {{token_api}}",
                                "type": "text"
                            }
                        ],
                        "body": {
                            "mode": "formdata",
                            "formdata": [
                                {
                                    "key": "name",
                                    "value": "New name",
                                    "type": "text"
                                }
                            ]
                        },
                        "url": {
                            "raw": "{{base_url}}vegetables/store",
                            "host": [
                                "{{base_url}}vegetables"
                            ],
                            "path": [
                                "store"
                            ]
                        }
                    },
                    "response": []
                },
                {
                    "name": "Update",
                    "request": {
                        "method": "PUT",
                        "header": [
                            {
                                "key": "Accept",
                                "value": "application/json",
                                "type": "text"
                            },
                            {
                                "key": "Authorization",
                                "value": "Bearer {{token_api}}",
                                "type": "text"
                            }
                        ],
                        "body": {
                            "mode": "urlencoded",
                            "urlencoded": [
                                {
                                    "key": "name",
                                    "value": "Update name",
                                    "type": "text"
                                }
                            ]
                        },
                        "url": {
                            "raw": "{{base_url}}vegetables/update/1",
                            "host": [
                                "{{base_url}}vegetables"
                            ],
                            "path": [
                                "update",
                                "1"
                            ]
                        }
                    },
                    "response": []
                },
                {
                    "name": "Delete",
                    "request": {
                        "method": "DELETE",
                        "header": [
                            {
                                "key": "Accept",
                                "value": "application/json",
                                "type": "text"
                            },
                            {
                                "key": "Authorization",
                                "value": "Bearer {{token_api}}",
                                "type": "text"
                            }
                        ],
                        "url": {
                            "raw": "{{base_url}}vegetables/delete/1",
                            "host": [
                                "{{base_url}}vegetables"
                            ],
                            "path": [
                                "delete",
                                "1"
                            ]
                        }
                    },
                    "response": []
                }
            ]
        }
    ]
}